INSTALL
LICENSE
MANIFEST.in
README.rst
setup.py
rediscluster/__init__.py
rediscluster/cluster_client.py
rediscluster.egg-info/PKG-INFO
rediscluster.egg-info/SOURCES.txt
rediscluster.egg-info/dependency_links.txt
rediscluster.egg-info/requires.txt
rediscluster.egg-info/top_level.txt