Metadata-Version: 1.1
Name: rediscluster
Version: 0.3.1
Summary: a Python interface to a Cluster of Redis key-value store
Home-page: http://github.com/salimane/rediscluster-py
Author: Salimane Adjao Moustapha
Author-email: me@salimane.com
License: Copyright (c) 2012 Salimane Adjao Moustapha
